attestable_mcp_server/__init__.py
attestable_mcp_server/__main__.py
attestable_mcp_server/server.py
iflow_mcp_co_browser_attestable_mcp_server-0.1.1.dist-info/METADATA
iflow_mcp_co_browser_attestable_mcp_server-0.1.1.dist-info/WHEEL
iflow_mcp_co_browser_attestable_mcp_server-0.1.1.dist-info/entry_points.txt
iflow_mcp_co_browser_attestable_mcp_server-0.1.1.dist-info/RECORD
