Metadata-Version: 2.4
Name: iflow-mcp_co-browser_attestable-mcp-server
Version: 0.1.1
Summary: Add your description here
Author-email: Ryan MacArthur <ryan.macarthur@gmail.com>
Requires-Python: >=3.11
Requires-Dist: anyio>=4.5
Requires-Dist: click>=8.0
Requires-Dist: docker>=7.1.0
Requires-Dist: fastapi>=0.115.12
Requires-Dist: httpx-sse>=0.4
Requires-Dist: httpx>=0.27
Requires-Dist: jinja2>=3.1.6
Requires-Dist: mcp>=1.0.0
Requires-Dist: pydantic-settings>=2.5.2
Requires-Dist: pydantic<3.0.0,>=2.7.2
Requires-Dist: pyyaml>=6.0.2
Requires-Dist: sse-starlette>=1.6.1
Requires-Dist: starlette>=0.27
Requires-Dist: tomli-w>=1.2.0
Requires-Dist: tomli>=2.2.1
Requires-Dist: uvicorn>=0.23.1
